[
  {
    "Letter": "İ",
    "Symbool NL": "NAALD",
    "Betekenis NL": "Goed nieuws",
    "Symbool TR": "İĞNE",
    "Betekenis TR": "Güzel haberler gelecek",
    "Symbool Engels": "NEEDLE",
    "Betekenis Engels": "Good news"
  },
  {
    "Letter": "İ",
    "Symbool NL": "OUDERE",
    "Betekenis NL": "Volgend jaar veel mooie ontwikkelingen",
    "Symbool TR": "İHTİYAR",
    "Betekenis TR": "Gelecek yıl güzel gelişmeler",
    "Symbool Engels": "ELDER",
    "Betekenis Engels": "Good progress next year"
  },
  {
    "Letter": "İ",
    "Symbool NL": "IMAM",
    "Betekenis NL": "Slecht nieuws",
    "Symbool TR": "İMAM",
    "Betekenis TR": "Kötü haber kapınızda",
    "Symbool Engels": "IMAM",
    "Betekenis Engels": "Bad news"
  },
  {
    "Letter": "İ",
    "Symbool NL": "KEIZER",
    "Betekenis NL": "Geld via kansspel",
    "Symbool TR": "İMPARATOR",
    "Betekenis TR": "Şans oyununda para",
    "Symbool Engels": "EMPEROR",
    "Betekenis Engels": "Money through gambling"
  },
  {
    "Letter": "İ",
    "Symbool NL": "PAREL",
    "Betekenis NL": "Innerlijke rust",
    "Symbool TR": "İNCİ",
    "Betekenis TR": "İçiniz huzurla dolacak",
    "Symbool Engels": "PEARL",
    "Betekenis Engels": "Inner peace"
  },
  {
    "Letter": "İ",
    "Symbool NL": "VIJGEN",
    "Betekenis NL": "Grote winst door korte reis",
    "Symbool TR": "İNCİR",
    "Betekenis TR": "Kısa yolculukla büyük kazanç",
    "Symbool Engels": "FIG",
    "Betekenis Engels": "Profit via short trip"
  },
  {
    "Letter": "İ",
    "Symbool NL": "MENS",
    "Betekenis NL": "Eén = rust; meerdere = problemen",
    "Symbool TR": "İNSAN",
    "Betekenis TR": "Tek kişi = huzur, iki+ = problem",
    "Symbool Engels": "HUMAN",
    "Betekenis Engels": "One = peace, many = problems"
  },
  {
    "Letter": "İ",
    "Symbool NL": "TOUW",
    "Betekenis NL": "Reis",
    "Symbool TR": "İP",
    "Betekenis TR": "Yolculuk",
    "Symbool Engels": "ROPE",
    "Betekenis Engels": "Journey"
  },
  {
    "Letter": "İ",
    "Symbool NL": "SPEELKAART",
    "Betekenis NL": "Zorgen verdwijnen door kleine inspanning",
    "Symbool TR": "İSKAMBİL",
    "Betekenis TR": "Büyük dertler kolay çabalarla bitecek",
    "Symbool Engels": "PLAYING CARD",
    "Betekenis Engels": "Troubles end with ease"
  },
  {
    "Letter": "İ",
    "Symbool NL": "LETTER İ",
    "Betekenis NL": "Geluk",
    "Symbool TR": "İ HARFİ",
    "Betekenis TR": "Şans",
    "Symbool Engels": "LETTER İ",
    "Betekenis Engels": "Luck"
  }
]