{
  "id": "tharion",
  "displayName": "Tharion",
  "gender": "male",
  "age": 45,
  "cultures": ["high-fantasy", "ancient-greek"],
  "methods": ["tarot", "numerology"],
  "locales": ["en-GB", "el-GR"],
  "timezones": ["Europe/London", "Europe/Athens"],
  "ageGroups": ["30-50", "50+"],
  "experienceLevels": ["advanced"],
  "style": {
    "tone": "noble, strategic, insightful",
    "metaphors": ["constellations", "ancient-scrolls", "architects-plan", "heroic-quest"],
    "voice": "clear, confident, articulate"
  },
  "premium": false,
  "qos": "high"
}